{
	"0": {
		"title": "In Hub Electric Longboard Motor",
		"image": "../../static/images/square/Hub_Motor_Assembly_Open.png",
		"hash": "#ElectricLongboard"
	},
	"1": {
		"title": "Stock Market Prediction Algorithm",
		"image": "../../static/images/square/StockDisplaySite.png",
		"hash": "#Mr.MarketWatch"
	},
	"2": {
		"title": "Telemetry Dashboard Gui",
		"image": "../../static/images/square/telemetry.png",
		"hash": "#TelemetrySpark"
	},
	"3": {
		"title": "Four Stage Climber Gearbox",
		"image": "../../static/images/square/ClimberSystemWinch.png",
		"hash": "#FIRST2018"
	},
	"4": {
		"title": "Breast Cancer Classification Algorithm",
		"image": "../../static/images/square/feature-comparison.png",
		"hash": "#BreastCancer"
	},
	"5": {
		"title": "Telemetry Sensor Schematic",
		"image": "../../static/images/square/Schematic.png",
		"hash": "#TelemetrySpark"
	},
	"6": {
		"title": "FIRST Robotics Climbing System",
		"image": "../../static/images/ClimberFullSystem.png",
		"hash": "#FIRST2018"
	},
	"7": {
		"title": "Yelp Review Sentiment Classifier Algorithm",
		"image": "../../static/images/yelp-review.png",
		"hash": "#SentimentAnalysis"
	},
	"8": {
		"title": "Custom Linear Algebra Equation Solving Library",
		"image": "../../static/images/linsystemsbg.png",
		"hash": "#LinearAlgebra"
	},
	"9": {
		"title": "Clothing Image Recognition ML Model",
		"image": "../../static/images/clothing-classifier.png",
		"hash": "#ClothingClassifier"
	},
	"10": {
		"title": "Torque Spring Motor",
		"image": "../../static/images/Negator Spring Motor.png",
		"hash": "#TorqueSpring"
	}
}